LICENSE
MANIFEST.in
setup.py
pytrac/__init__.py
pytrac/ticket.py
pytrac.egg-info/PKG-INFO
pytrac.egg-info/SOURCES.txt
pytrac.egg-info/dependency_links.txt
pytrac.egg-info/requires.txt
pytrac.egg-info/top_level.txt
rst/HISTORY.rst
rst/README.rst
test/test_ticket.py