Metadata-Version: 1.0
Name: pytrac
Version: 0.4
Summary: Library for managing TRAC tickets with Python
Home-page: https://github.com/Jimdo/pytrac
Author: Daniel Bonkowski, Pirmin Fix
Author-email: bonko@jimdo.com, pirmin.fix@jimdo.com
License: Apache
Platform: UNKNOWN
